ppftpy/__init__.py
ppftpy/_ppft2.py
ppftpy/_ppft3.py
ppftpy/_utils.py
ppftpy/_version.py
ppftpy/py.typed
ppft_py-0.1.0.dist-info/METADATA
ppft_py-0.1.0.dist-info/WHEEL
ppft_py-0.1.0.dist-info/licenses/LICENSE
ppft_py-0.1.0.dist-info/RECORD
