Metadata-Version: 2.4
Name: ppft-py
Version: 0.1.0
Summary: Highly optimized Pseudo-Polar Fourier Transform in Python
Project-URL: Homepage, https://github.com/jnk22/ppft-py
Project-URL: Repository, https://github.com/jnk22/ppft-py
Project-URL: Documentation, https://ppft-py.readthedocs.io
Author-email: Jannik Schäfer <jannik.schaefer@inbox-online.de>
License-Expression: MIT
License-File: LICENSE
Keywords: fft,ppft
Classifier: Development Status :: 4 - Beta
Classifier: Intended Audience :: Developers
Classifier: Intended Audience :: Science/Research
Classifier: License :: OSI Approved :: MIT License
Classifier: Programming Language :: Python
Classifier: Programming Language :: Python :: 3
Classifier: Programming Language :: Python :: 3.10
Classifier: Programming Language :: Python :: 3.11
Classifier: Programming Language :: Python :: 3.12
Classifier: Programming Language :: Python :: 3.13
Classifier: Topic :: Software Development :: Libraries :: Python Modules
Requires-Python: <4,>=3.10
Requires-Dist: array-api-compat>=1.9
